{
  "cuentas": {
    "cabecera": {
      "dato": {
        "id": 1,
        "usuario": "leo",
        "estado": true,
        "contrasenia": "YXR1bg\u003d\u003d",
        "persona": {
          "id": 1,
          "nombres": "leo",
          "apellidos": "leo",
          "fechaNacimiento": "Mar 4, 2004 12:00:00 AM",
          "identificacion": "1105986689",
          "tipoIdentificacion": "CEDULA",
          "estado": true,
          "correo": "asd@ymial.com"
        }
      }
    },
    "tamanio": 1
  }
}